infi.run_as-0.1.12-py3.7-nspkg.pth
infi/run_as/__init__.py
infi/run_as/__version__.py
infi/run_as/c_api/__init__.py
infi.run_as-0.1.12.dist-info/LICENSE
infi.run_as-0.1.12.dist-info/METADATA
infi.run_as-0.1.12.dist-info/WHEEL
infi.run_as-0.1.12.dist-info/entry_points.txt
infi.run_as-0.1.12.dist-info/namespace_packages.txt
infi.run_as-0.1.12.dist-info/top_level.txt
infi.run_as-0.1.12.dist-info/RECORD
